README.md
setup.py
alibabacloud_darabonba_string/__init__.py
alibabacloud_darabonba_string/client.py
alibabacloud_darabonba_string.egg-info/PKG-INFO
alibabacloud_darabonba_string.egg-info/SOURCES.txt
alibabacloud_darabonba_string.egg-info/dependency_links.txt
alibabacloud_darabonba_string.egg-info/top_level.txt